Metadata-Version: 2.1
Name: django-user-sessions
Version: 2.0.0
Summary: Django sessions with a foreign key to the user
Home-page: http://github.com/jazzband/django-user-sessions
Download-URL: https://pypi.python.org/pypi/django-user-sessions
Author: Bouke Haarsma
Author-email: bouke@haarsma.eu
License: MIT
Classifier: Development Status :: 5 - Production/Stable
Classifier: Environment :: Web Environment
Classifier: Framework :: Django
Classifier: Framework :: Django :: 3.2
Classifier: Framework :: Django :: 4.0
Classifier: Intended Audience :: Developers
Classifier: License :: OSI Approved :: MIT License
Classifier: Operating System :: OS Independent
Classifier: Programming Language :: Python
Classifier: Programming Language :: Python :: 3
Classifier: Programming Language :: Python :: 3.7
Classifier: Programming Language :: Python :: 3.8
Classifier: Programming Language :: Python :: 3.9
Classifier: Programming Language :: Python :: 3.10
Classifier: Topic :: Security
License-File: LICENSE
